moleva/__init__.py
moleva/libs/__init__.cpython-38-x86_64-linux-gnu.so
moleva/libs/admet_model.cpython-38-x86_64-linux-gnu.so
moleva/libs/config.cpython-38-x86_64-linux-gnu.so
moleva/libs/evaluator.cpython-38-x86_64-linux-gnu.so
moleva/libs/exceptions.cpython-38-x86_64-linux-gnu.so
moleva/libs/fp_calculator.cpython-38-x86_64-linux-gnu.so
moleva/libs/license_verify.cpython-38-x86_64-linux-gnu.so
moleva/libs/logging_helper.cpython-38-x86_64-linux-gnu.so
moleva/libs/logs_scorer.cpython-38-x86_64-linux-gnu.so
moleva/libs/model_decrypt.cpython-38-x86_64-linux-gnu.so
moleva/libs/pubchemfp.cpython-38-x86_64-linux-gnu.so
moleva-0.0.19.dist-info/METADATA
moleva-0.0.19.dist-info/WHEEL
moleva-0.0.19.dist-info/top_level.txt
moleva-0.0.19.dist-info/RECORD
