Metadata-Version: 2.1
Name: moleva
Version: 0.0.19
Summary: evaluate molecule properties
License: MIT
Requires-Python: >=3.8
Requires-Dist: retrying (>=1.3.3)
Requires-Dist: pyyaml (>=6.0)
Requires-Dist: mordred (>=1.2.0)
Requires-Dist: xgboost (>=1.6.2)
Requires-Dist: deepchem (>=2.6.1)
Requires-Dist: rdkit (<2023.3.1,>=2022.3.5)
Requires-Dist: numpy (>=1.23.3)
Requires-Dist: descriptastorus (>=2.6.0)
Requires-Dist: scipy
Requires-Dist: pycrypto (>=2.6.1)
Requires-Dist: cryptography (>=41.0.3)
Requires-Dist: mol2vec (>=0.2.2)
